{
	"configurations" : 
	[
		{
			"directories" : 
			[
				{
					"build" : ".",
					"jsonFile" : "directory-.-Debug-d0094a50bb2071803777.json",
					"minimumCMakeVersion" : 
					{
						"string" : "3.10"
					},
					"projectIndex" : 0,
					"source" : ".",
					"targetIndexes" : 
					[
						0,
						1,
						2,
						3
					]
				}
			],
			"name" : "Debug",
			"projects" : 
			[
				{
					"directoryIndexes" : 
					[
						0
					],
					"name" : "ChatApp",
					"targetIndexes" : 
					[
						0,
						1,
						2,
						3
					]
				}
			],
			"targets" : 
			[
				{
					"directoryIndex" : 0,
					"id" : "ALL_BUILD::@6890427a1f51a3e7e1df",
					"jsonFile" : "target-ALL_BUILD-Debug-5ba56f3b69cffd8da009.json",
					"name" : "ALL_BUILD",
					"projectIndex" : 0
				},
				{
					"directoryIndex" : 0,
					"id" : "ZERO_CHECK::@6890427a1f51a3e7e1df",
					"jsonFile" : "target-ZERO_CHECK-Debug-66e4fe257d6896ad28a0.json",
					"name" : "ZERO_CHECK",
					"projectIndex" : 0
				},
				{
					"directoryIndex" : 0,
					"id" : "client::@6890427a1f51a3e7e1df",
					"jsonFile" : "target-client-Debug-350565f3021a64f31e50.json",
					"name" : "client",
					"projectIndex" : 0
				},
				{
					"directoryIndex" : 0,
					"id" : "server::@6890427a1f51a3e7e1df",
					"jsonFile" : "target-server-Debug-5d2b6dd03c1777e848e7.json",
					"name" : "server",
					"projectIndex" : 0
				}
			]
		},
		{
			"directories" : 
			[
				{
					"build" : ".",
					"jsonFile" : "directory-.-Release-d0094a50bb2071803777.json",
					"minimumCMakeVersion" : 
					{
						"string" : "3.10"
					},
					"projectIndex" : 0,
					"source" : ".",
					"targetIndexes" : 
					[
						0,
						1,
						2,
						3
					]
				}
			],
			"name" : "Release",
			"projects" : 
			[
				{
					"directoryIndexes" : 
					[
						0
					],
					"name" : "ChatApp",
					"targetIndexes" : 
					[
						0,
						1,
						2,
						3
					]
				}
			],
			"targets" : 
			[
				{
					"directoryIndex" : 0,
					"id" : "ALL_BUILD::@6890427a1f51a3e7e1df",
					"jsonFile" : "target-ALL_BUILD-Release-5ba56f3b69cffd8da009.json",
					"name" : "ALL_BUILD",
					"projectIndex" : 0
				},
				{
					"directoryIndex" : 0,
					"id" : "ZERO_CHECK::@6890427a1f51a3e7e1df",
					"jsonFile" : "target-ZERO_CHECK-Release-66e4fe257d6896ad28a0.json",
					"name" : "ZERO_CHECK",
					"projectIndex" : 0
				},
				{
					"directoryIndex" : 0,
					"id" : "client::@6890427a1f51a3e7e1df",
					"jsonFile" : "target-client-Release-65f826b0101cb50430ac.json",
					"name" : "client",
					"projectIndex" : 0
				},
				{
					"directoryIndex" : 0,
					"id" : "server::@6890427a1f51a3e7e1df",
					"jsonFile" : "target-server-Release-483d5dd3cc4de2aa46f2.json",
					"name" : "server",
					"projectIndex" : 0
				}
			]
		},
		{
			"directories" : 
			[
				{
					"build" : ".",
					"jsonFile" : "directory-.-MinSizeRel-d0094a50bb2071803777.json",
					"minimumCMakeVersion" : 
					{
						"string" : "3.10"
					},
					"projectIndex" : 0,
					"source" : ".",
					"targetIndexes" : 
					[
						0,
						1,
						2,
						3
					]
				}
			],
			"name" : "MinSizeRel",
			"projects" : 
			[
				{
					"directoryIndexes" : 
					[
						0
					],
					"name" : "ChatApp",
					"targetIndexes" : 
					[
						0,
						1,
						2,
						3
					]
				}
			],
			"targets" : 
			[
				{
					"directoryIndex" : 0,
					"id" : "ALL_BUILD::@6890427a1f51a3e7e1df",
					"jsonFile" : "target-ALL_BUILD-MinSizeRel-5ba56f3b69cffd8da009.json",
					"name" : "ALL_BUILD",
					"projectIndex" : 0
				},
				{
					"directoryIndex" : 0,
					"id" : "ZERO_CHECK::@6890427a1f51a3e7e1df",
					"jsonFile" : "target-ZERO_CHECK-MinSizeRel-66e4fe257d6896ad28a0.json",
					"name" : "ZERO_CHECK",
					"projectIndex" : 0
				},
				{
					"directoryIndex" : 0,
					"id" : "client::@6890427a1f51a3e7e1df",
					"jsonFile" : "target-client-MinSizeRel-198922ae0da1679ab74d.json",
					"name" : "client",
					"projectIndex" : 0
				},
				{
					"directoryIndex" : 0,
					"id" : "server::@6890427a1f51a3e7e1df",
					"jsonFile" : "target-server-MinSizeRel-fee9b2c1fa302b2c31ef.json",
					"name" : "server",
					"projectIndex" : 0
				}
			]
		},
		{
			"directories" : 
			[
				{
					"build" : ".",
					"jsonFile" : "directory-.-RelWithDebInfo-d0094a50bb2071803777.json",
					"minimumCMakeVersion" : 
					{
						"string" : "3.10"
					},
					"projectIndex" : 0,
					"source" : ".",
					"targetIndexes" : 
					[
						0,
						1,
						2,
						3
					]
				}
			],
			"name" : "RelWithDebInfo",
			"projects" : 
			[
				{
					"directoryIndexes" : 
					[
						0
					],
					"name" : "ChatApp",
					"targetIndexes" : 
					[
						0,
						1,
						2,
						3
					]
				}
			],
			"targets" : 
			[
				{
					"directoryIndex" : 0,
					"id" : "ALL_BUILD::@6890427a1f51a3e7e1df",
					"jsonFile" : "target-ALL_BUILD-RelWithDebInfo-5ba56f3b69cffd8da009.json",
					"name" : "ALL_BUILD",
					"projectIndex" : 0
				},
				{
					"directoryIndex" : 0,
					"id" : "ZERO_CHECK::@6890427a1f51a3e7e1df",
					"jsonFile" : "target-ZERO_CHECK-RelWithDebInfo-66e4fe257d6896ad28a0.json",
					"name" : "ZERO_CHECK",
					"projectIndex" : 0
				},
				{
					"directoryIndex" : 0,
					"id" : "client::@6890427a1f51a3e7e1df",
					"jsonFile" : "target-client-RelWithDebInfo-0bf098069f30d2f0a80c.json",
					"name" : "client",
					"projectIndex" : 0
				},
				{
					"directoryIndex" : 0,
					"id" : "server::@6890427a1f51a3e7e1df",
					"jsonFile" : "target-server-RelWithDebInfo-a9af6dd757cac9fb3e00.json",
					"name" : "server",
					"projectIndex" : 0
				}
			]
		}
	],
	"kind" : "codemodel",
	"paths" : 
	{
		"build" : "E:/boostpz/build",
		"source" : "E:/boostpz"
	},
	"version" : 
	{
		"major" : 2,
		"minor" : 5
	}
}
